{
  "url": "https://netstrata.com.au/public-health-orders-for-strata-environments/",
  "timestamp": "2025-11-03T17:51:39.054214",
  "success": true,
  "content": {
    "title": "Public Health Orders for Strata Environments",
    "date": "2020-05-28T13:41:19+00:00",
    "category": null,
    "author": "S J",
    "main_content": "As of May 15, COVID-19 Public Health Orders regarding what we can do in strata environments have changed.\n\nThe NSW Fair Trading page provides information for you who are living and working in strata schemes.\n\nAdditionally, our website has a collection of Frequently Asked Questions for what we are doing for our clients during COVID-19 and beyond, as well as your Strata Manager who has direct information regarding your Scheme.\n\nhttps://www.netstrata.com.au/managing-your-scheme-through-covid-19/\n\nhttps://www.fairtrading.nsw.gov.au/resource-library/publications/coronavirus-covid-19/covid-19-strata-guidelines\n\n### Subscribe to our newsletter\n\nBy signing up to our monthly newsletter, you’ll be the first to get the latest news and updates from our team.\n\n[SUBSCRIBE](https://netstrata.com.au/subscribe/)",
    "images": []
  }
}