{
  "url": "https://netstrata.com.au/what-do-strata-levies-pay-for/",
  "timestamp": "2025-11-03T18:04:44.097833",
  "success": true,
  "content": {
    "title": "What do Strata Levies pay for?",
    "date": "2010-06-24T11:09:52+00:00",
    "category": null,
    "author": "S J",
    "main_content": "What Do Strata Levies Pay For?\n\nStrata Levies contribute to the operating expenses of strata properties and are divided into 2 separate funds being:\n\nAdministration Fund – intended for current operating costs; such as:\n\nInsurances\nGeneral Maintenance of shared or what’s known as common property\nMowing and gardening of common property\nCleaning of common property\nWater consumption\nElectricity Costs\n\nIn a perfect world the administration fund would have a $0 balance as you only budget for what you spend.\n\nSinking Fund – intended for the long-term maintenance of the buildings and improvements to the property, such as:\n\nReplacing common area carpets\nRepainting of common areas\nReplacement of guttering\nReplacement of garage door\n\nHow and when are levies determined?\n\nLevy contributions are reviewed yearly by the owners at their annual general meeting, the amount of levies you pay is determined by the owners at the meeting based on the budget sent out with the meeting notice, it is important to look at the meeting notice carefully so you are fully aware what your levies are likely to be.",
    "images": []
  }
}